uno/__init__.py
pyuno_game-0.0.4.dist-info/LICENSE
pyuno_game-0.0.4.dist-info/METADATA
pyuno_game-0.0.4.dist-info/WHEEL
pyuno_game-0.0.4.dist-info/top_level.txt
pyuno_game-0.0.4.dist-info/RECORD
