Metadata-Version: 2.1
Name: pyuno-game
Version: 0.0.4
Summary: A uno game
Author-email: Dorapower <thatisluo@outlook.com>
License: MIT License
Project-URL: Homepage, https://github.com/Dorapower/Uno-Game
Project-URL: Documentation, https://github.com/Dorapower/Uno-Game/wiki
Project-URL: Repository, https://github.com/Dorapower/Uno-Game.git
Keywords: uno,game
Classifier: Development Status :: 1 - Planning
Classifier: Programming Language :: Python :: 3
Classifier: Operating System :: OS Independent
Classifier: License :: OSI Approved :: MIT License
Classifier: Intended Audience :: Developers
Classifier: Topic :: Games/Entertainment :: Board Games
Classifier: Typing :: Typed
License-File: LICENSE
